{
  "1": "阿昌族",
  "2": "白族",
  "3": "保安族",
  "4": "布朗族",
  "5": "布依族",
  "6": "中国的朝鲜族",
  "7": "达干尔族",
  "8": "傣族",
  "9": "德昂族",
  "10": "东乡族 ",
  "11": "侗族",
  "12": "独龙族",
  "13": "我国的俄罗斯族",
  "14": "鄂伦春人",
  "15": "鄂温克族",
  "16": "高山族",
  "17": "仡佬族",
  "18": "哈尼族",
  "19": "哈萨克族",
  "20": "汉族  ",
  "21": "赫哲族",
  "22": "回族",
  "23": "基诺族",
  "24": "京族",
  "25": "景颇族",
  "26": "柯尔克孜族",
  "27": "拉祜族",
  "28": "黎族",
  "29": "傈僳族",
  "30": "珞巴族",
  "31": "满族",
  "32": "毛南族",
  "33": "门巴族 ",
  "34": "蒙古族",
  "35": "苗族",
  "36": "仫佬族族 ",
  "37": "纳西族",
  "38":  "怒族",
  "39": "普米族",
  "40": "羌族",
  "41": "撒拉族",
  "42": "畲族",
  "43": "水族",
  "44": "塔塔尔族 ",
  "45": "塔吉克族",
  "46": "土家族",
  "47": "土族",
  "48": "佤族",
  "49": "维吾尔族",
  "50": "乌孜别克族",
  "51": "锡伯族",
  "52": "瑶族",
  "53": "彝族",
  "54": "裕固族",
  "55": "藏族",
  "56": "壮族"
}
